twitter_conversation/__init__.py
twitter_conversation/obtain.py
twitter_conversation/scripts/reply_tree.py
twitter_conversation-1.1.dist-info/METADATA
twitter_conversation-1.1.dist-info/WHEEL
twitter_conversation-1.1.dist-info/entry_points.txt
twitter_conversation-1.1.dist-info/RECORD
