Metadata-Version: 2.1
Name: twitter-conversation
Version: 1.1
Summary: This is a project to obtain Twitter conversation over the Twitter-API v2 and to store them as csv.
License: CC BY-NC-SA 4.0
Author: Marc Feger
Author-email: marc.feger@icloud.com
Requires-Python: >=3.10,<4.0
Classifier: Framework :: Pytest
Classifier: Intended Audience :: Developers
Classifier: Intended Audience :: Science/Research
Classifier: License :: OSI Approved :: Common Public License
Classifier: License :: Other/Proprietary License
Classifier: Natural Language :: English
Classifier: Programming Language :: Python :: 3
Classifier: Programming Language :: Python :: 3.10
Classifier: Programming Language :: Python :: 3.11
Classifier: Topic :: Database
Classifier: Topic :: Database :: Database Engines/Servers
Classifier: Topic :: Internet
Classifier: Topic :: Scientific/Engineering :: Artificial Intelligence
Classifier: Topic :: Scientific/Engineering :: Information Analysis
Classifier: Topic :: Scientific/Engineering :: Visualization
Classifier: Topic :: Software Development :: Libraries :: Application Frameworks
Classifier: Topic :: Software Development :: Quality Assurance
Requires-Dist: pandas (>=1.4.3,<2.0.0)
Requires-Dist: tqdm (>=4.64.1,<5.0.0)
Requires-Dist: tweepy (>=4.10.0,<5.0.0)
